barbacoa/__init__.py
barbacoa/version.json
barbacoa/backends/__init__.py
barbacoa/plugins/__init__.py
barbacoa/plugins/dirs.py
barbacoa/plugins/exc.py
barbacoa/plugins/loader.py
barbacoa/plugins/scanner.py
barbacoa/plugins/struct.py
barbacoa/plugins/mods/__init__.py
barbacoa/plugins/mods/tools/__init__.py
barbacoa/plugins/mods/tools/loop.py
barbacoa/plugins/mods/tools/pack.py
barbacoa/plugins/mods/tools/pinger.py
barbacoa/plugins/mods/tools/test.py
barbacoa/queues/__init__.py
barbacoa/storage/__init__.py
barbacoa/tasks/__init__.py
barbacoa-0.2.3.dist-info/entry_points.txt
barbacoa-0.2.3.dist-info/LICENSE
barbacoa-0.2.3.dist-info/WHEEL
barbacoa-0.2.3.dist-info/METADATA
barbacoa-0.2.3.dist-info/RECORD
